setup.py
mess_server_amk.egg-info/PKG-INFO
mess_server_amk.egg-info/SOURCES.txt
mess_server_amk.egg-info/dependency_links.txt
mess_server_amk.egg-info/requires.txt
mess_server_amk.egg-info/top_level.txt
server/__init__.py
server/server.py
server/common/__init__.py
server/common/decorators.py
server/common/descriptors.py
server/common/errors.py
server/common/metaclasses.py
server/common/settings.py
server/common/utils.py
server/logs/__init__.py
server/logs/client_log_config.py
server/logs/server_log_config.py
server/server/__init__.py
server/server/add_user.py
server/server/config_win.py
server/server/main_win.py
server/server/remove_user.py
server/server/server_core.py
server/server/server_db.py
server/server/stat_win.py