Metadata-Version: 1.0
Name: mess-server-amk
Version: 0.0.1
Summary: mess_server_amk
Home-page: UNKNOWN
Author: Kolotov Alexander
Author-email: amk@yandex.ru
License: UNKNOWN
Platform: UNKNOWN
